langtrain/__init__.py
langtrain/example.py
langtrain/model_zoo.py
langtrain/agents/__init__.py
langtrain/callbacks/__init__.py
langtrain/callbacks/base.py
langtrain/callbacks/early_stopping.py
langtrain/callbacks/logging.py
langtrain/callbacks/registry.py
langtrain/cli/__init__.py
langtrain/cli/finetune.py
langtrain/cli/train.py
langtrain/components/__init__.py
langtrain/components/attention.py
langtrain/components/mlp.py
langtrain/components/patch_embedding.py
langtrain/config/__init__.py
langtrain/data/__init__.py
langtrain/data/datasets.py
langtrain/filesystem/__init__.py
langtrain/llm/__init__.py
langtrain/memory/__init__.py
langtrain/models/__init__.py
langtrain/models/lora.py
langtrain/models/vision_transformer.py
langtrain/sync/__init__.py
langtrain/telemetry/__init__.py
langtrain/training/__init__.py
langtrain/training/trainer.py
langtrain/utils/__init__.py
langtrain/utils/config.py
langtrain/utils/cuda.py
langtrain/utils/data.py
langtrain/utils/device.py
langtrain_ai-0.0.3.dist-info/licenses/LICENSE
langtrain_ai-0.0.3.dist-info/METADATA
langtrain_ai-0.0.3.dist-info/WHEEL
langtrain_ai-0.0.3.dist-info/entry_points.txt
langtrain_ai-0.0.3.dist-info/top_level.txt
langtrain_ai-0.0.3.dist-info/RECORD
