Metadata-Version: 2.4
Name: langtrain-ai
Version: 0.0.3
Summary: Vision LLMs with Efficient LoRA Fine-Tuning
Author-email: Pritesh Raj <priteshraj10@gmail.com>
License: MIT License
Project-URL: Homepage, https://github.com/langtrain-ai/langtrain
Project-URL: Documentation, https://github.com/langtrain-ai/langtrain/tree/main/docs
Project-URL: Source, https://github.com/langtrain-ai/langtrain
Project-URL: Tracker, https://github.com/langtrain-ai/langtrain/issues
Requires-Python: >=3.8
License-File: LICENSE
Requires-Dist: torch>=1.10
Requires-Dist: numpy
Requires-Dist: tqdm
Requires-Dist: pyyaml
Requires-Dist: scipy
Requires-Dist: matplotlib
Requires-Dist: pillow
Dynamic: license-file
